[{"line":1,"elements":[{"line":4,"name":"","description":"","type":"background","keyword":"Background","steps":[{"name":"url 'http:\/\/localhost:9897'","result":{"duration":89100,"status":"passed"},"match":{"location":"karate","arguments":[]},"keyword":"Given","line":5,"doc_string":{"content_type":"","value":"09:56:05.112 karate.env system property was: prod \n","line":5}}]},{"start_timestamp":"2022-09-05T06:56:05.111Z","line":7,"name":"To update the Job Entry for exiting job in JSON format","description":"","id":"to-update-the-job-entry-for-exiting-job-in-json-format","type":"scenario","keyword":"Scenario","steps":[{"name":"path '\/normal\/webapi\/add'","result":{"duration":45101,"status":"passed"},"match":{"location":"karate","arguments":[]},"comments":["# Create a new Job Entry","# Update the Job Entry using PUT request","# Using jsonPath verify the updation of details in Job Entry"],"keyword":"Given","line":11},{"name":"def getRandomValue = function(){return Math.floor((100)*Math.random());}","result":{"duration":141199,"status":"passed"},"match":{"location":"karate","arguments":[]},"keyword":"*","line":12},{"name":"def id = getRandomValue()","result":{"duration":223801,"status":"passed"},"match":{"location":"karate","arguments":[]},"keyword":"*","line":13},{"name":"request {\"jobId\": '#(id)',\"jobTitle\":\"Software Engg - 2\",\"jobDescription\":\"To develop andriod application\",\"experience\":[\"Google\",\"Apple\",\"Mobile Iron\",\"Subex\"],\"project\":[{\"projectName\":\"Movie App\",\"technology\":[\"Kotlin\",\"SQL Lite\",\"Gradle\",\"Jenkins\"]}]}","result":{"duration":546100,"status":"passed"},"match":{"location":"karate","arguments":[]},"keyword":"And","line":14},{"name":"headers {Accept: 'application\/json', Content-Type: 'application\/json'}","result":{"duration":141200,"status":"passed"},"match":{"location":"karate","arguments":[]},"keyword":"And","line":15},{"name":"method post","result":{"duration":21420201,"status":"passed"},"match":{"location":"karate","arguments":[]},"keyword":"When","line":16,"doc_string":{"content_type":"","value":"09:56:05.117 request:\n1 > POST http:\/\/localhost:9897\/normal\/webapi\/add\n1 > Accept: application\/json\n1 > Content-Type: application\/json; charset=UTF-8\n1 > Content-Length: 241\n1 > Host: localhost:9897\n1 > Connection: Keep-Alive\n1 > User-Agent: Apache-HttpClient\/4.5.13 (Java\/18.0.1.1)\n1 > Accept-Encoding: gzip,deflate\n{\"jobId\":35,\"jobTitle\":\"Software Engg - 2\",\"jobDescription\":\"To develop andriod application\",\"experience\":[\"Google\",\"Apple\",\"Mobile Iron\",\"Subex\"],\"project\":[{\"projectName\":\"Movie App\",\"technology\":[\"Kotlin\",\"SQL Lite\",\"Gradle\",\"Jenkins\"]}]}\n\n09:56:05.135 response time in milliseconds: 17\n1 < 201\n1 < X-Content-Type-Options: nosniff\n1 < X-XSS-Protection: 1; mode=block\n1 < Cache-Control: no-cache, no-store, max-age=0, must-revalidate\n1 < Pragma: no-cache\n1 < Expires: 0\n1 < X-Frame-Options: DENY\n1 < Content-Type: application\/json\n1 < Transfer-Encoding: chunked\n1 < Date: Mon, 05 Sep 2022 06:56:04 GMT\n1 < Keep-Alive: timeout=60\n1 < Connection: keep-alive\n{\"jobId\":35,\"jobTitle\":\"Software Engg - 2\",\"jobDescription\":\"To develop andriod application\",\"experience\":[\"Google\",\"Apple\",\"Mobile Iron\",\"Subex\"],\"project\":[{\"projectName\":\"Movie App\",\"technology\":[\"Kotlin\",\"SQL Lite\",\"Gradle\",\"Jenkins\"]}]}\n\n","line":16}},{"name":"status 201","result":{"duration":31701,"status":"passed"},"match":{"location":"karate","arguments":[]},"keyword":"And","line":17},{"name":"path '\/normal\/webapi\/update'","result":{"duration":495600,"status":"passed"},"match":{"location":"karate","arguments":[]},"comments":["#PUT request"],"keyword":"Given","line":19},{"name":"request","result":{"duration":505799,"status":"passed"},"match":{"location":"karate","arguments":[]},"keyword":"And","line":20,"doc_string":{"content_type":"","value":"{\n    \"jobId\": '#(id)',\n    \"jobTitle\": \"Software Engg - 3\",\n    \"jobDescription\": \"To develop andriod application and Web application\",\n    \"experience\": [\n        \"Google\",\n        \"Apple\",\n        \"Mobile Iron\"\n    ],\n    \"project\": [\n        {\n            \"projectName\": \"Movie App\",\n            \"technology\": [\n                \"Kotlin\",\n                \"SQL Lite\",\n                \"Gradle\",\n                \"Jenkins\"\n            ]\n        },\n        {\n            \"projectName\": \"Web App\",\n            \"technology\": [\n                \"Kotlin\",\n                \"SQL Lite\",\n                \"Gradle\",\n                \"Node Js\"\n            ]\n        }\n    ]\n}","line":20}},{"name":"headers {Accept: 'application\/json', Content-Type: 'application\/json'}","result":{"duration":180300,"status":"passed"},"match":{"location":"karate","arguments":[]},"keyword":"And","line":53},{"name":"method put","result":{"duration":15877600,"status":"passed"},"match":{"location":"karate","arguments":[]},"keyword":"When","line":54,"doc_string":{"content_type":"","value":"09:56:05.140 request:\n2 > PUT http:\/\/localhost:9897\/normal\/webapi\/update\n2 > Accept: application\/json\n2 > Content-Type: application\/json; charset=UTF-8\n2 > Content-Length: 333\n2 > Host: localhost:9897\n2 > Connection: Keep-Alive\n2 > User-Agent: Apache-HttpClient\/4.5.13 (Java\/18.0.1.1)\n2 > Accept-Encoding: gzip,deflate\n{\"jobId\":35,\"jobTitle\":\"Software Engg - 3\",\"jobDescription\":\"To develop andriod application and Web application\",\"experience\":[\"Google\",\"Apple\",\"Mobile Iron\"],\"project\":[{\"projectName\":\"Movie App\",\"technology\":[\"Kotlin\",\"SQL Lite\",\"Gradle\",\"Jenkins\"]},{\"projectName\":\"Web App\",\"technology\":[\"Kotlin\",\"SQL Lite\",\"Gradle\",\"Node Js\"]}]}\n\n09:56:05.153 response time in milliseconds: 11\n2 < 200\n2 < X-Content-Type-Options: nosniff\n2 < X-XSS-Protection: 1; mode=block\n2 < Cache-Control: no-cache, no-store, max-age=0, must-revalidate\n2 < Pragma: no-cache\n2 < Expires: 0\n2 < X-Frame-Options: DENY\n2 < Content-Type: application\/json\n2 < Transfer-Encoding: chunked\n2 < Date: Mon, 05 Sep 2022 06:56:04 GMT\n2 < Keep-Alive: timeout=60\n2 < Connection: keep-alive\n{\"jobId\":35,\"jobTitle\":\"Software Engg - 3\",\"jobDescription\":\"To develop andriod application and Web application\",\"experience\":[\"Google\",\"Apple\",\"Mobile Iron\"],\"project\":[{\"projectName\":\"Movie App\",\"technology\":[\"Kotlin\",\"SQL Lite\",\"Gradle\",\"Jenkins\"]},{\"projectName\":\"Web App\",\"technology\":[\"Kotlin\",\"SQL Lite\",\"Gradle\",\"Node Js\"]}]}\n\n","line":54}},{"name":"status 200","result":{"duration":31699,"status":"passed"},"match":{"location":"karate","arguments":[]},"keyword":"Then","line":55},{"name":"def projectArray = karate.jsonPath(response, \"$[?(@.jobId == \"+ id +\")].project\")","result":{"duration":1734400,"status":"passed"},"match":{"location":"karate","arguments":[]},"keyword":"*","line":56},{"name":"print projectArray","result":{"duration":7022801,"status":"passed"},"match":{"location":"karate","arguments":[]},"keyword":"And","line":57,"doc_string":{"content_type":"","value":"09:56:05.162 [print] [\n  [\n    {\n      \"projectName\": \"Movie App\",\n      \"technology\": [\n        \"Kotlin\",\n        \"SQL Lite\",\n        \"Gradle\",\n        \"Jenkins\"\n      ]\n    },\n    {\n      \"projectName\": \"Web App\",\n      \"technology\": [\n        \"Kotlin\",\n        \"SQL Lite\",\n        \"Gradle\",\n        \"Node Js\"\n      ]\n    }\n  ]\n]\n \n","line":57}},{"name":"match projectArray[0] == '#[2]'","result":{"duration":2139101,"status":"passed"},"match":{"location":"karate","arguments":[]},"keyword":"And","line":58}],"tags":[]},{"line":4,"name":"","description":"","type":"background","keyword":"Background","steps":[{"name":"url 'http:\/\/localhost:9897'","result":{"duration":213400,"status":"passed"},"match":{"location":"karate","arguments":[]},"keyword":"Given","line":5,"doc_string":{"content_type":"","value":"09:56:05.174 karate.env system property was: prod \n","line":5}}]},{"start_timestamp":"2022-09-05T06:56:05.173Z","line":60,"name":"To update the Job Entry for exiting job in JSON format","description":"","id":"to-update-the-job-entry-for-exiting-job-in-json-format","type":"scenario","keyword":"Scenario","steps":[{"name":"path '\/normal\/webapi\/add'","result":{"duration":92300,"status":"passed"},"match":{"location":"karate","arguments":[]},"comments":["# Create a new Job Entry","# Update the Job Entry using PUT request","# Using jsonPath verify the updation of details in Job Entry"],"keyword":"Given","line":64},{"name":"def getRandomValue = function(){return Math.floor((100)*Math.random());}","result":{"duration":256000,"status":"passed"},"match":{"location":"karate","arguments":[]},"keyword":"*","line":65},{"name":"def id = getRandomValue()","result":{"duration":241000,"status":"passed"},"match":{"location":"karate","arguments":[]},"keyword":"*","line":66},{"name":"request {\"jobId\": '#(id)',\"jobTitle\":\"Software Engg - 2\",\"jobDescription\":\"To develop andriod application\",\"experience\":[\"Google\",\"Apple\",\"Mobile Iron\",\"Subex\"],\"project\":[{\"projectName\":\"Movie App\",\"technology\":[\"Kotlin\",\"SQL Lite\",\"Gradle\",\"Jenkins\"]}]}","result":{"duration":858100,"status":"passed"},"match":{"location":"karate","arguments":[]},"keyword":"And","line":67},{"name":"headers {Accept: 'application\/json', Content-Type: 'application\/json'}","result":{"duration":124400,"status":"passed"},"match":{"location":"karate","arguments":[]},"keyword":"And","line":68},{"name":"method post","result":{"duration":52886300,"status":"passed"},"match":{"location":"karate","arguments":[]},"keyword":"When","line":69,"doc_string":{"content_type":"","value":"09:56:05.219 request:\n1 > POST http:\/\/localhost:9897\/normal\/webapi\/add\n1 > Accept: application\/json\n1 > Content-Type: application\/json; charset=UTF-8\n1 > Content-Length: 241\n1 > Host: localhost:9897\n1 > Connection: Keep-Alive\n1 > User-Agent: Apache-HttpClient\/4.5.13 (Java\/18.0.1.1)\n1 > Accept-Encoding: gzip,deflate\n{\"jobId\":84,\"jobTitle\":\"Software Engg - 2\",\"jobDescription\":\"To develop andriod application\",\"experience\":[\"Google\",\"Apple\",\"Mobile Iron\",\"Subex\"],\"project\":[{\"projectName\":\"Movie App\",\"technology\":[\"Kotlin\",\"SQL Lite\",\"Gradle\",\"Jenkins\"]}]}\n\n09:56:05.230 response time in milliseconds: 10\n1 < 201\n1 < X-Content-Type-Options: nosniff\n1 < X-XSS-Protection: 1; mode=block\n1 < Cache-Control: no-cache, no-store, max-age=0, must-revalidate\n1 < Pragma: no-cache\n1 < Expires: 0\n1 < X-Frame-Options: DENY\n1 < Content-Type: application\/json\n1 < Transfer-Encoding: chunked\n1 < Date: Mon, 05 Sep 2022 06:56:04 GMT\n1 < Keep-Alive: timeout=60\n1 < Connection: keep-alive\n{\"jobId\":84,\"jobTitle\":\"Software Engg - 2\",\"jobDescription\":\"To develop andriod application\",\"experience\":[\"Google\",\"Apple\",\"Mobile Iron\",\"Subex\"],\"project\":[{\"projectName\":\"Movie App\",\"technology\":[\"Kotlin\",\"SQL Lite\",\"Gradle\",\"Jenkins\"]}]}\n\n","line":69}},{"name":"status 201","result":{"duration":26700,"status":"passed"},"match":{"location":"karate","arguments":[]},"keyword":"And","line":70},{"name":"path '\/normal\/webapi\/update'","result":{"duration":877500,"status":"passed"},"match":{"location":"karate","arguments":[]},"comments":["#PUT request"],"keyword":"Given","line":72},{"name":"request","result":{"duration":203700,"status":"passed"},"match":{"location":"karate","arguments":[]},"keyword":"And","line":73,"doc_string":{"content_type":"","value":"{\n    \"jobId\": 55455,\n    \"jobTitle\": \"Software Engg - 3\",\n    \"jobDescription\": \"To develop andriod application and Web application\",\n    \"experience\": [\n        \"Google\",\n        \"Apple\",\n        \"Mobile Iron\"\n    ],\n    \"project\": [\n        {\n            \"projectName\": \"Movie App\",\n            \"technology\": [\n                \"Kotlin\",\n                \"SQL Lite\",\n                \"Gradle\",\n                \"Jenkins\"\n            ]\n        },\n        {\n            \"projectName\": \"Web App\",\n            \"technology\": [\n                \"Kotlin\",\n                \"SQL Lite\",\n                \"Gradle\",\n                \"Node Js\"\n            ]\n        }\n    ]\n}","line":73}},{"name":"headers {Accept: 'application\/json', Content-Type: 'application\/json'}","result":{"duration":87400,"status":"passed"},"match":{"location":"karate","arguments":[]},"keyword":"And","line":106},{"name":"method put","result":{"duration":19243700,"status":"passed"},"match":{"location":"karate","arguments":[]},"keyword":"When","line":107,"doc_string":{"content_type":"","value":"09:56:05.236 request:\n2 > PUT http:\/\/localhost:9897\/normal\/webapi\/update\n2 > Accept: application\/json\n2 > Content-Type: application\/json; charset=UTF-8\n2 > Content-Length: 336\n2 > Host: localhost:9897\n2 > Connection: Keep-Alive\n2 > User-Agent: Apache-HttpClient\/4.5.13 (Java\/18.0.1.1)\n2 > Accept-Encoding: gzip,deflate\n{\"jobId\":55455,\"jobTitle\":\"Software Engg - 3\",\"jobDescription\":\"To develop andriod application and Web application\",\"experience\":[\"Google\",\"Apple\",\"Mobile Iron\"],\"project\":[{\"projectName\":\"Movie App\",\"technology\":[\"Kotlin\",\"SQL Lite\",\"Gradle\",\"Jenkins\"]},{\"projectName\":\"Web App\",\"technology\":[\"Kotlin\",\"SQL Lite\",\"Gradle\",\"Node Js\"]}]}\n\n09:56:05.251 response time in milliseconds: 13\n2 < 404\n2 < X-Content-Type-Options: nosniff\n2 < X-XSS-Protection: 1; mode=block\n2 < Cache-Control: no-cache, no-store, max-age=0, must-revalidate\n2 < Pragma: no-cache\n2 < Expires: 0\n2 < X-Frame-Options: DENY\n2 < Content-Type: application\/json\n2 < Transfer-Encoding: chunked\n2 < Date: Mon, 05 Sep 2022 06:56:04 GMT\n2 < Keep-Alive: timeout=60\n2 < Connection: keep-alive\n{\"message\":\"Failed to update Entry [jobId=55455, jobTitle=Software Engg - 3, jobDescription=To develop andriod application and Web application, experience=[Ljava.lang.Object;@4c3d581c, project=[[projectName=Movie App, technology=[Kotlin, SQL Lite, Gradle, Jenkins]], [projectName=Web App, technology=[Kotlin, SQL Lite, Gradle, Node Js]]]]\"}\n\n","line":107}},{"name":"status 404","result":{"duration":25400,"status":"passed"},"match":{"location":"karate","arguments":[]},"keyword":"Then","line":108}],"tags":[]},{"line":4,"name":"","description":"","type":"background","keyword":"Background","steps":[{"name":"url 'http:\/\/localhost:9897'","result":{"duration":212101,"status":"passed"},"match":{"location":"karate","arguments":[]},"keyword":"Given","line":5,"doc_string":{"content_type":"","value":"09:56:05.169 karate.env system property was: prod \n","line":5}}]},{"start_timestamp":"2022-09-05T06:56:05.167Z","line":110,"name":"To update the Job Entry for exiting job in JSON format by calling another feature file","description":"","id":"to-update-the-job-entry-for-exiting-job-in-json-format-by-calling-another-feature-file","type":"scenario","keyword":"Scenario","steps":[{"name":"call read(\"..\/createJobEntry.feature\")","result":{"duration":29102900,"status":"passed"},"match":{"location":"karate","arguments":[]},"comments":["# <Gherkin keyword> <call> <read(<location of file>)>"],"keyword":"Given","line":112},{"name":"com\/api\/automation\/putrequest\/..\/createJobEntry.feature","result":{"duration":0,"status":"passed"},"match":{"location":"karate","arguments":[]},"keyword":"","line":112},{"name":"url 'http:\/\/localhost:9897'","result":{"duration":108700,"status":"passed"},"match":{"location":"karate","arguments":[]},"keyword":"> Given","line":5},{"name":"path '\/normal\/webapi\/add'","result":{"duration":49200,"status":"passed"},"match":{"location":"karate","arguments":[]},"keyword":"> And","line":6},{"name":"def getRandomValue = function(){return Math.floor((100)*Math.random());}","result":{"duration":205200,"status":"passed"},"match":{"location":"karate","arguments":[]},"keyword":"> *","line":7},{"name":"def id = getRandomValue()","result":{"duration":269200,"status":"passed"},"match":{"location":"karate","arguments":[]},"keyword":"> *","line":8},{"name":"request {\"jobId\":'#(id)',\"jobTitle\":\"Software Engg - 2\",\"jobDescription\":\"To develop andriod application\",\"experience\":[\"Google\",\"Apple\",\"Mobile Iron\",\"Subex\"],\"project\":[{\"projectName\":\"Movie App\",\"technology\":[\"Kotlin\",\"SQL Lite\",\"Gradle\",\"Jenkins\"]}]}","result":{"duration":306199,"status":"passed"},"match":{"location":"karate","arguments":[]},"keyword":"> And","line":9},{"name":"headers {Accept: 'application\/json', Content-Type: 'application\/json'}","result":{"duration":119300,"status":"passed"},"match":{"location":"karate","arguments":[]},"keyword":"> And","line":10},{"name":"method post","result":{"duration":18667601,"status":"passed"},"match":{"location":"karate","arguments":[]},"keyword":"> When","line":11,"doc_string":{"content_type":"","value":"09:56:05.181 request:\n1 > POST http:\/\/localhost:9897\/normal\/webapi\/add\n1 > Accept: application\/json\n1 > Content-Type: application\/json; charset=UTF-8\n1 > Content-Length: 241\n1 > Host: localhost:9897\n1 > Connection: Keep-Alive\n1 > User-Agent: Apache-HttpClient\/4.5.13 (Java\/18.0.1.1)\n1 > Accept-Encoding: gzip,deflate\n{\"jobId\":70,\"jobTitle\":\"Software Engg - 2\",\"jobDescription\":\"To develop andriod application\",\"experience\":[\"Google\",\"Apple\",\"Mobile Iron\",\"Subex\"],\"project\":[{\"projectName\":\"Movie App\",\"technology\":[\"Kotlin\",\"SQL Lite\",\"Gradle\",\"Jenkins\"]}]}\n\n09:56:05.196 response time in milliseconds: 12\n1 < 201\n1 < X-Content-Type-Options: nosniff\n1 < X-XSS-Protection: 1; mode=block\n1 < Cache-Control: no-cache, no-store, max-age=0, must-revalidate\n1 < Pragma: no-cache\n1 < Expires: 0\n1 < X-Frame-Options: DENY\n1 < Content-Type: application\/json\n1 < Transfer-Encoding: chunked\n1 < Date: Mon, 05 Sep 2022 06:56:04 GMT\n1 < Keep-Alive: timeout=60\n1 < Connection: keep-alive\n{\"jobId\":70,\"jobTitle\":\"Software Engg - 2\",\"jobDescription\":\"To develop andriod application\",\"experience\":[\"Google\",\"Apple\",\"Mobile Iron\",\"Subex\"],\"project\":[{\"projectName\":\"Movie App\",\"technology\":[\"Kotlin\",\"SQL Lite\",\"Gradle\",\"Jenkins\"]}]}\n\n","line":11}},{"name":"status 201","result":{"duration":25100,"status":"passed"},"match":{"location":"karate","arguments":[]},"keyword":"> And","line":12},{"name":"def responseJobId = response.jobId","result":{"duration":358699,"status":"passed"},"match":{"location":"karate","arguments":[]},"keyword":"> *","line":13},{"name":"path '\/normal\/webapi\/update'","result":{"duration":214400,"status":"passed"},"match":{"location":"karate","arguments":[]},"comments":["#PUT request"],"keyword":"Given","line":114},{"name":"request","result":{"duration":171400,"status":"passed"},"match":{"location":"karate","arguments":[]},"keyword":"And","line":115,"doc_string":{"content_type":"","value":"{\n    \"jobId\":125,\n    \"jobTitle\": \"Software Engg - 3\",\n    \"jobDescription\": \"To develop andriod application and Web application\",\n    \"experience\": [\n        \"Google\",\n        \"Apple\",\n        \"Mobile Iron\"\n    ],\n    \"project\": [\n        {\n            \"projectName\": \"Movie App\",\n            \"technology\": [\n                \"Kotlin\",\n                \"SQL Lite\",\n                \"Gradle\",\n                \"Jenkins\"\n            ]\n        },\n        {\n            \"projectName\": \"Web App\",\n            \"technology\": [\n                \"Kotlin\",\n                \"SQL Lite\",\n                \"Gradle\",\n                \"Node Js\"\n            ]\n        }\n    ]\n}","line":115}},{"name":"headers {Accept: 'application\/json', Content-Type: 'application\/json'}","result":{"duration":77201,"status":"passed"},"match":{"location":"karate","arguments":[]},"keyword":"And","line":148},{"name":"method put","result":{"duration":18238501,"status":"passed"},"match":{"location":"karate","arguments":[]},"keyword":"When","line":149,"doc_string":{"content_type":"","value":"09:56:05.209 request:\n2 > PUT http:\/\/localhost:9897\/normal\/webapi\/update\n2 > Accept: application\/json\n2 > Content-Type: application\/json; charset=UTF-8\n2 > Content-Length: 334\n2 > Host: localhost:9897\n2 > Connection: Keep-Alive\n2 > User-Agent: Apache-HttpClient\/4.5.13 (Java\/18.0.1.1)\n2 > Accept-Encoding: gzip,deflate\n{\"jobId\":125,\"jobTitle\":\"Software Engg - 3\",\"jobDescription\":\"To develop andriod application and Web application\",\"experience\":[\"Google\",\"Apple\",\"Mobile Iron\"],\"project\":[{\"projectName\":\"Movie App\",\"technology\":[\"Kotlin\",\"SQL Lite\",\"Gradle\",\"Jenkins\"]},{\"projectName\":\"Web App\",\"technology\":[\"Kotlin\",\"SQL Lite\",\"Gradle\",\"Node Js\"]}]}\n\n09:56:05.217 response time in milliseconds: 7\n2 < 404\n2 < X-Content-Type-Options: nosniff\n2 < X-XSS-Protection: 1; mode=block\n2 < Cache-Control: no-cache, no-store, max-age=0, must-revalidate\n2 < Pragma: no-cache\n2 < Expires: 0\n2 < X-Frame-Options: DENY\n2 < Content-Type: application\/json\n2 < Transfer-Encoding: chunked\n2 < Date: Mon, 05 Sep 2022 06:56:04 GMT\n2 < Keep-Alive: timeout=60\n2 < Connection: keep-alive\n{\"message\":\"Failed to update Entry [jobId=125, jobTitle=Software Engg - 3, jobDescription=To develop andriod application and Web application, experience=[Ljava.lang.Object;@6cc3bf4d, project=[[projectName=Movie App, technology=[Kotlin, SQL Lite, Gradle, Jenkins]], [projectName=Web App, technology=[Kotlin, SQL Lite, Gradle, Node Js]]]]\"}\n\n","line":149}},{"name":"status 200","result":{"duration":114400,"error_message":"status code was: 404, expected: 200, response time in milliseconds: 7, url: http:\/\/localhost:9897\/normal\/webapi\/update, response: \n{\"message\":\"Failed to update Entry [jobId=125, jobTitle=Software Engg - 3, jobDescription=To develop andriod application and Web application, experience=[Ljava.lang.Object;@6cc3bf4d, project=[[projectName=Movie App, technology=[Kotlin, SQL Lite, Gradle, Jenkins]], [projectName=Web App, technology=[Kotlin, SQL Lite, Gradle, Node Js]]]]\"}\nclasspath:com\/api\/automation\/putrequest\/updateJobEntry.feature:150","status":"failed"},"match":{"location":"karate","arguments":[]},"keyword":"Then","line":150,"doc_string":{"content_type":"","value":"09:56:05.221 classpath:com\/api\/automation\/putrequest\/updateJobEntry.feature:150\nThen status 200\nstatus code was: 404, expected: 200, response time in milliseconds: 7, url: http:\/\/localhost:9897\/normal\/webapi\/update, response: \n{\"message\":\"Failed to update Entry [jobId=125, jobTitle=Software Engg - 3, jobDescription=To develop andriod application and Web application, experience=[Ljava.lang.Object;@6cc3bf4d, project=[[projectName=Movie App, technology=[Kotlin, SQL Lite, Gradle, Jenkins]], [projectName=Web App, technology=[Kotlin, SQL Lite, Gradle, Node Js]]]]\"}\nclasspath:com\/api\/automation\/putrequest\/updateJobEntry.feature:150\n","line":150}},{"name":"def projectArray = karate.jsonPath(response, \"$[?(@.jobId == 125)].project\")","result":{"duration":0,"status":"skipped"},"match":{"location":"karate","arguments":[]},"keyword":"*","line":151},{"name":"print projectArray","result":{"duration":0,"status":"skipped"},"match":{"location":"karate","arguments":[]},"keyword":"And","line":152},{"name":"match projectArray[0] == '#[2]'","result":{"duration":0,"status":"skipped"},"match":{"location":"karate","arguments":[]},"keyword":"And","line":153}],"tags":[]},{"line":4,"name":"","description":"","type":"background","keyword":"Background","steps":[{"name":"url 'http:\/\/localhost:9897'","result":{"duration":137701,"status":"passed"},"match":{"location":"karate","arguments":[]},"keyword":"Given","line":5,"doc_string":{"content_type":"","value":"09:56:05.227 karate.env system property was: prod \n","line":5}}]},{"start_timestamp":"2022-09-05T06:56:05.225Z","line":155,"name":"To update the Job Entry for exiting job in JSON format by calling another feature file","description":"","id":"to-update-the-job-entry-for-exiting-job-in-json-format-by-calling-another-feature-file","type":"scenario","keyword":"Scenario","steps":[{"name":"def postRequest = call read(\"..\/createJobEntry.feature\")","result":{"duration":37994700,"status":"passed"},"match":{"location":"karate","arguments":[]},"comments":["# <Gherkin keyword> <call> <read(<location of file>)>","# Given call read(\"..\/createJobEntry.feature\")"],"keyword":"*","line":158},{"name":"com\/api\/automation\/putrequest\/..\/createJobEntry.feature","result":{"duration":0,"status":"passed"},"match":{"location":"karate","arguments":[]},"keyword":"","line":158},{"name":"url 'http:\/\/localhost:9897'","result":{"duration":142301,"status":"passed"},"match":{"location":"karate","arguments":[]},"keyword":"> Given","line":5},{"name":"path '\/normal\/webapi\/add'","result":{"duration":31999,"status":"passed"},"match":{"location":"karate","arguments":[]},"keyword":"> And","line":6},{"name":"def getRandomValue = function(){return Math.floor((100)*Math.random());}","result":{"duration":293600,"status":"passed"},"match":{"location":"karate","arguments":[]},"keyword":"> *","line":7},{"name":"def id = getRandomValue()","result":{"duration":312800,"status":"passed"},"match":{"location":"karate","arguments":[]},"keyword":"> *","line":8},{"name":"request {\"jobId\":'#(id)',\"jobTitle\":\"Software Engg - 2\",\"jobDescription\":\"To develop andriod application\",\"experience\":[\"Google\",\"Apple\",\"Mobile Iron\",\"Subex\"],\"project\":[{\"projectName\":\"Movie App\",\"technology\":[\"Kotlin\",\"SQL Lite\",\"Gradle\",\"Jenkins\"]}]}","result":{"duration":242201,"status":"passed"},"match":{"location":"karate","arguments":[]},"keyword":"> And","line":9},{"name":"headers {Accept: 'application\/json', Content-Type: 'application\/json'}","result":{"duration":110100,"status":"passed"},"match":{"location":"karate","arguments":[]},"keyword":"> And","line":10},{"name":"method post","result":{"duration":28831199,"status":"passed"},"match":{"location":"karate","arguments":[]},"keyword":"> When","line":11,"doc_string":{"content_type":"","value":"09:56:05.242 request:\n1 > POST http:\/\/localhost:9897\/normal\/webapi\/add\n1 > Accept: application\/json\n1 > Content-Type: application\/json; charset=UTF-8\n1 > Content-Length: 241\n1 > Host: localhost:9897\n1 > Connection: Keep-Alive\n1 > User-Agent: Apache-HttpClient\/4.5.13 (Java\/18.0.1.1)\n1 > Accept-Encoding: gzip,deflate\n{\"jobId\":82,\"jobTitle\":\"Software Engg - 2\",\"jobDescription\":\"To develop andriod application\",\"experience\":[\"Google\",\"Apple\",\"Mobile Iron\",\"Subex\"],\"project\":[{\"projectName\":\"Movie App\",\"technology\":[\"Kotlin\",\"SQL Lite\",\"Gradle\",\"Jenkins\"]}]}\n\n09:56:05.253 response time in milliseconds: 8\n1 < 201\n1 < X-Content-Type-Options: nosniff\n1 < X-XSS-Protection: 1; mode=block\n1 < Cache-Control: no-cache, no-store, max-age=0, must-revalidate\n1 < Pragma: no-cache\n1 < Expires: 0\n1 < X-Frame-Options: DENY\n1 < Content-Type: application\/json\n1 < Transfer-Encoding: chunked\n1 < Date: Mon, 05 Sep 2022 06:56:04 GMT\n1 < Keep-Alive: timeout=60\n1 < Connection: keep-alive\n{\"jobId\":82,\"jobTitle\":\"Software Engg - 2\",\"jobDescription\":\"To develop andriod application\",\"experience\":[\"Google\",\"Apple\",\"Mobile Iron\",\"Subex\"],\"project\":[{\"projectName\":\"Movie App\",\"technology\":[\"Kotlin\",\"SQL Lite\",\"Gradle\",\"Jenkins\"]}]}\n\n","line":11}},{"name":"status 201","result":{"duration":24500,"status":"passed"},"match":{"location":"karate","arguments":[]},"keyword":"> And","line":12},{"name":"def responseJobId = response.jobId","result":{"duration":1405900,"status":"passed"},"match":{"location":"karate","arguments":[]},"keyword":"> *","line":13},{"name":"print \"Calling Feature ==> \", postRequest.id","result":{"duration":2422100,"status":"passed"},"match":{"location":"karate","arguments":[]},"keyword":"And","line":159,"doc_string":{"content_type":"","value":"09:56:05.268 [print] Calling Feature ==>  82 \n","line":159}},{"name":"print \"Calling Feature ==> \", postRequest.getRandomValue()","result":{"duration":2968301,"status":"passed"},"match":{"location":"karate","arguments":[]},"keyword":"And","line":160,"doc_string":{"content_type":"","value":"09:56:05.271 [print] Calling Feature ==>  98 \n","line":160}},{"name":"path '\/normal\/webapi\/update'","result":{"duration":371299,"status":"passed"},"match":{"location":"karate","arguments":[]},"comments":["#PUT request"],"keyword":"Given","line":162},{"name":"request","result":{"duration":694400,"status":"passed"},"match":{"location":"karate","arguments":[]},"keyword":"And","line":163,"doc_string":{"content_type":"","value":"{\n    \"jobId\":'#(postRequest.id)',\n    \"jobTitle\": \"Software Engg - 3\",\n    \"jobDescription\": \"To develop andriod application and Web application\",\n    \"experience\": [\n        \"Google\",\n        \"Apple\",\n        \"Mobile Iron\"\n    ],\n    \"project\": [\n        {\n            \"projectName\": \"Movie App\",\n            \"technology\": [\n                \"Kotlin\",\n                \"SQL Lite\",\n                \"Gradle\",\n                \"Jenkins\"\n            ]\n        },\n        {\n            \"projectName\": \"Web App\",\n            \"technology\": [\n                \"Kotlin\",\n                \"SQL Lite\",\n                \"Gradle\",\n                \"Node Js\"\n            ]\n        }\n    ]\n}","line":163}},{"name":"headers {Accept: 'application\/json', Content-Type: 'application\/json'}","result":{"duration":152500,"status":"passed"},"match":{"location":"karate","arguments":[]},"keyword":"And","line":196},{"name":"method put","result":{"duration":15135700,"status":"passed"},"match":{"location":"karate","arguments":[]},"keyword":"When","line":197,"doc_string":{"content_type":"","value":"09:56:05.275 request:\n2 > PUT http:\/\/localhost:9897\/normal\/webapi\/update\n2 > Accept: application\/json\n2 > Content-Type: application\/json; charset=UTF-8\n2 > Content-Length: 333\n2 > Host: localhost:9897\n2 > Connection: Keep-Alive\n2 > User-Agent: Apache-HttpClient\/4.5.13 (Java\/18.0.1.1)\n2 > Accept-Encoding: gzip,deflate\n{\"jobId\":82,\"jobTitle\":\"Software Engg - 3\",\"jobDescription\":\"To develop andriod application and Web application\",\"experience\":[\"Google\",\"Apple\",\"Mobile Iron\"],\"project\":[{\"projectName\":\"Movie App\",\"technology\":[\"Kotlin\",\"SQL Lite\",\"Gradle\",\"Jenkins\"]},{\"projectName\":\"Web App\",\"technology\":[\"Kotlin\",\"SQL Lite\",\"Gradle\",\"Node Js\"]}]}\n\n09:56:05.287 response time in milliseconds: 9\n2 < 200\n2 < X-Content-Type-Options: nosniff\n2 < X-XSS-Protection: 1; mode=block\n2 < Cache-Control: no-cache, no-store, max-age=0, must-revalidate\n2 < Pragma: no-cache\n2 < Expires: 0\n2 < X-Frame-Options: DENY\n2 < Content-Type: application\/json\n2 < Transfer-Encoding: chunked\n2 < Date: Mon, 05 Sep 2022 06:56:04 GMT\n2 < Keep-Alive: timeout=60\n2 < Connection: keep-alive\n{\"jobId\":82,\"jobTitle\":\"Software Engg - 3\",\"jobDescription\":\"To develop andriod application and Web application\",\"experience\":[\"Google\",\"Apple\",\"Mobile Iron\"],\"project\":[{\"projectName\":\"Movie App\",\"technology\":[\"Kotlin\",\"SQL Lite\",\"Gradle\",\"Jenkins\"]},{\"projectName\":\"Web App\",\"technology\":[\"Kotlin\",\"SQL Lite\",\"Gradle\",\"Node Js\"]}]}\n\n","line":197}},{"name":"status 200","result":{"duration":31501,"status":"passed"},"match":{"location":"karate","arguments":[]},"keyword":"Then","line":198},{"name":"def projectArray = karate.jsonPath(response, \"$[?(@.jobId == \"+ postRequest.id +\")].project\")","result":{"duration":1610201,"status":"passed"},"match":{"location":"karate","arguments":[]},"keyword":"*","line":199},{"name":"print projectArray","result":{"duration":4094901,"status":"passed"},"match":{"location":"karate","arguments":[]},"keyword":"And","line":200,"doc_string":{"content_type":"","value":"09:56:05.294 [print] [\n  [\n    {\n      \"projectName\": \"Movie App\",\n      \"technology\": [\n        \"Kotlin\",\n        \"SQL Lite\",\n        \"Gradle\",\n        \"Jenkins\"\n      ]\n    },\n    {\n      \"projectName\": \"Web App\",\n      \"technology\": [\n        \"Kotlin\",\n        \"SQL Lite\",\n        \"Gradle\",\n        \"Node Js\"\n      ]\n    }\n  ]\n]\n \n","line":200}},{"name":"match projectArray[0] == '#[2]'","result":{"duration":1643500,"status":"passed"},"match":{"location":"karate","arguments":[]},"keyword":"And","line":201}],"tags":[]},{"line":4,"name":"","description":"","type":"background","keyword":"Background","steps":[{"name":"url 'http:\/\/localhost:9897'","result":{"duration":151900,"status":"passed"},"match":{"location":"karate","arguments":[]},"keyword":"Given","line":5,"doc_string":{"content_type":"","value":"09:56:05.274 karate.env system property was: prod \n","line":5}}]},{"start_timestamp":"2022-09-05T06:56:05.270Z","line":203,"name":"To update the Job Entry for exiting job in JSON format by calling another feature file with cariable","description":"","id":"to-update-the-job-entry-for-exiting-job-in-json-format-by-calling-another-feature-file-with-cariable","type":"scenario","keyword":"Scenario","steps":[{"name":"def getRandomValue = function(){return Math.floor((100)*Math.random());}","result":{"duration":5089500,"status":"passed"},"match":{"location":"karate","arguments":[]},"comments":["# <Gherkin keyword> <call> <read(<location of file>)>","# Given call read (\"..\/createJobEntry.feature\"){var1:value, var2:value}"],"keyword":"*","line":206},{"name":"def id = getRandomValue()","result":{"duration":9577200,"status":"passed"},"match":{"location":"karate","arguments":[]},"keyword":"*","line":207},{"name":"def postRequest = call read(\"..\/createJobEntryWithVariables.feature\"){_url:'http:\/\/localhost:9897', _path:'\/normal\/webapi\/add', _id:'#(id)'}","result":{"duration":57846900,"status":"passed"},"match":{"location":"karate","arguments":[]},"keyword":"*","line":208},{"name":"com\/api\/automation\/putrequest\/..\/createJobEntryWithVariables.feature","result":{"duration":0,"status":"passed"},"match":{"location":"karate","arguments":[]},"keyword":"","line":208},{"name":"url _url","result":{"duration":205500,"status":"passed"},"match":{"location":"karate","arguments":[]},"keyword":"> Given","line":5},{"name":"path _path","result":{"duration":1166800,"status":"passed"},"match":{"location":"karate","arguments":[]},"keyword":"> And","line":6},{"name":"print \"Helper ==> \", _url","result":{"duration":5093700,"status":"passed"},"match":{"location":"karate","arguments":[]},"keyword":"> And","line":7,"doc_string":{"content_type":"","value":"09:56:05.314 [print] Helper ==>  http:\/\/localhost:9897 \n","line":7}},{"name":"print \"Helper ==> \", _path","result":{"duration":4433601,"status":"passed"},"match":{"location":"karate","arguments":[]},"keyword":"> And","line":8,"doc_string":{"content_type":"","value":"09:56:05.319 [print] Helper ==>  \/normal\/webapi\/add \n","line":8}},{"name":"print \"Helper ==> \", _id","result":{"duration":5643000,"status":"passed"},"match":{"location":"karate","arguments":[]},"keyword":"> And","line":9,"doc_string":{"content_type":"","value":"09:56:05.326 [print] Helper ==>  22 \n","line":9}},{"name":"request {\"jobId\":'#(_id)',\"jobTitle\":\"Software Engg - 2\",\"jobDescription\":\"To develop andriod application\",\"experience\":[\"Google\",\"Apple\",\"Mobile Iron\",\"Subex\"],\"project\":[{\"projectName\":\"Movie App\",\"technology\":[\"Kotlin\",\"SQL Lite\",\"Gradle\",\"Jenkins\"]}]}","result":{"duration":1884301,"status":"passed"},"match":{"location":"karate","arguments":[]},"keyword":"> And","line":10},{"name":"headers {Accept: 'application\/json', Content-Type: 'application\/json'}","result":{"duration":210000,"status":"passed"},"match":{"location":"karate","arguments":[]},"keyword":"> And","line":11},{"name":"method post","result":{"duration":20304700,"status":"passed"},"match":{"location":"karate","arguments":[]},"keyword":"> When","line":12,"doc_string":{"content_type":"","value":"09:56:05.333 request:\n1 > POST http:\/\/localhost:9897\/normal\/webapi\/add\n1 > Accept: application\/json\n1 > Content-Type: application\/json; charset=UTF-8\n1 > Content-Length: 241\n1 > Host: localhost:9897\n1 > Connection: Keep-Alive\n1 > User-Agent: Apache-HttpClient\/4.5.13 (Java\/18.0.1.1)\n1 > Accept-Encoding: gzip,deflate\n{\"jobId\":22,\"jobTitle\":\"Software Engg - 2\",\"jobDescription\":\"To develop andriod application\",\"experience\":[\"Google\",\"Apple\",\"Mobile Iron\",\"Subex\"],\"project\":[{\"projectName\":\"Movie App\",\"technology\":[\"Kotlin\",\"SQL Lite\",\"Gradle\",\"Jenkins\"]}]}\n\n09:56:05.348 response time in milliseconds: 14\n1 < 201\n1 < X-Content-Type-Options: nosniff\n1 < X-XSS-Protection: 1; mode=block\n1 < Cache-Control: no-cache, no-store, max-age=0, must-revalidate\n1 < Pragma: no-cache\n1 < Expires: 0\n1 < X-Frame-Options: DENY\n1 < Content-Type: application\/json\n1 < Transfer-Encoding: chunked\n1 < Date: Mon, 05 Sep 2022 06:56:04 GMT\n1 < Keep-Alive: timeout=60\n1 < Connection: keep-alive\n{\"jobId\":22,\"jobTitle\":\"Software Engg - 2\",\"jobDescription\":\"To develop andriod application\",\"experience\":[\"Google\",\"Apple\",\"Mobile Iron\",\"Subex\"],\"project\":[{\"projectName\":\"Movie App\",\"technology\":[\"Kotlin\",\"SQL Lite\",\"Gradle\",\"Jenkins\"]}]}\n\n","line":12}},{"name":"status 201","result":{"duration":30800,"status":"passed"},"match":{"location":"karate","arguments":[]},"keyword":"> And","line":13},{"name":"def responseJobId = response.jobId","result":{"duration":1043100,"status":"passed"},"match":{"location":"karate","arguments":[]},"keyword":"> *","line":14},{"name":"def responseJobTitle = response.jobTitle","result":{"duration":758901,"status":"passed"},"match":{"location":"karate","arguments":[]},"keyword":"> *","line":15},{"name":"path '\/normal\/webapi\/update'","result":{"duration":1069100,"status":"passed"},"match":{"location":"karate","arguments":[]},"comments":["#PUT request"],"keyword":"Given","line":210},{"name":"request","result":{"duration":524800,"status":"passed"},"match":{"location":"karate","arguments":[]},"keyword":"And","line":211,"doc_string":{"content_type":"","value":"{\n    \"jobId\":'#(id)',\n    \"jobTitle\": \"Software Engg - 3\",\n    \"jobDescription\": \"To develop andriod application and Web application\",\n    \"experience\": [\n        \"Google\",\n        \"Apple\",\n        \"Mobile Iron\"\n    ],\n    \"project\": [\n        {\n            \"projectName\": \"Movie App\",\n            \"technology\": [\n                \"Kotlin\",\n                \"SQL Lite\",\n                \"Gradle\",\n                \"Jenkins\"\n            ]\n        },\n        {\n            \"projectName\": \"Web App\",\n            \"technology\": [\n                \"Kotlin\",\n                \"SQL Lite\",\n                \"Gradle\",\n                \"Node Js\"\n            ]\n        }\n    ]\n}","line":211}},{"name":"headers {Accept: 'application\/json', Content-Type: 'application\/json'}","result":{"duration":137700,"status":"passed"},"match":{"location":"karate","arguments":[]},"keyword":"And","line":244},{"name":"method put","result":{"duration":14018101,"status":"passed"},"match":{"location":"karate","arguments":[]},"keyword":"When","line":245,"doc_string":{"content_type":"","value":"09:56:05.358 request:\n2 > PUT http:\/\/localhost:9897\/normal\/webapi\/update\n2 > Accept: application\/json\n2 > Content-Type: application\/json; charset=UTF-8\n2 > Content-Length: 333\n2 > Host: localhost:9897\n2 > Connection: Keep-Alive\n2 > User-Agent: Apache-HttpClient\/4.5.13 (Java\/18.0.1.1)\n2 > Accept-Encoding: gzip,deflate\n{\"jobId\":22,\"jobTitle\":\"Software Engg - 3\",\"jobDescription\":\"To develop andriod application and Web application\",\"experience\":[\"Google\",\"Apple\",\"Mobile Iron\"],\"project\":[{\"projectName\":\"Movie App\",\"technology\":[\"Kotlin\",\"SQL Lite\",\"Gradle\",\"Jenkins\"]},{\"projectName\":\"Web App\",\"technology\":[\"Kotlin\",\"SQL Lite\",\"Gradle\",\"Node Js\"]}]}\n\n09:56:05.367 response time in milliseconds: 7\n2 < 200\n2 < X-Content-Type-Options: nosniff\n2 < X-XSS-Protection: 1; mode=block\n2 < Cache-Control: no-cache, no-store, max-age=0, must-revalidate\n2 < Pragma: no-cache\n2 < Expires: 0\n2 < X-Frame-Options: DENY\n2 < Content-Type: application\/json\n2 < Transfer-Encoding: chunked\n2 < Date: Mon, 05 Sep 2022 06:56:04 GMT\n2 < Keep-Alive: timeout=60\n2 < Connection: keep-alive\n{\"jobId\":22,\"jobTitle\":\"Software Engg - 3\",\"jobDescription\":\"To develop andriod application and Web application\",\"experience\":[\"Google\",\"Apple\",\"Mobile Iron\"],\"project\":[{\"projectName\":\"Movie App\",\"technology\":[\"Kotlin\",\"SQL Lite\",\"Gradle\",\"Jenkins\"]},{\"projectName\":\"Web App\",\"technology\":[\"Kotlin\",\"SQL Lite\",\"Gradle\",\"Node Js\"]}]}\n\n","line":245}},{"name":"status 200","result":{"duration":22300,"status":"passed"},"match":{"location":"karate","arguments":[]},"keyword":"Then","line":246},{"name":"def projectArray = karate.jsonPath(response, \"$[?(@.jobId == \"+ id +\")].project\")","result":{"duration":1705600,"status":"passed"},"match":{"location":"karate","arguments":[]},"keyword":"*","line":247},{"name":"print projectArray","result":{"duration":4781900,"status":"passed"},"match":{"location":"karate","arguments":[]},"keyword":"And","line":248,"doc_string":{"content_type":"","value":"09:56:05.373 [print] [\n  [\n    {\n      \"projectName\": \"Movie App\",\n      \"technology\": [\n        \"Kotlin\",\n        \"SQL Lite\",\n        \"Gradle\",\n        \"Jenkins\"\n      ]\n    },\n    {\n      \"projectName\": \"Web App\",\n      \"technology\": [\n        \"Kotlin\",\n        \"SQL Lite\",\n        \"Gradle\",\n        \"Node Js\"\n      ]\n    }\n  ]\n]\n \n","line":248}},{"name":"match projectArray[0] == '#[2]'","result":{"duration":2421400,"status":"passed"},"match":{"location":"karate","arguments":[]},"keyword":"And","line":249}],"tags":[]}],"name":"com\/api\/automation\/putrequest\/updateJobEntry.feature","description":"To test the updation of Job entry in the test application\nTest the end point PUT \/noral\/webapi\/update","id":"to-test-the-updation-of-job-entry-in-the-test-application","keyword":"Feature","uri":"com\/api\/automation\/putrequest\/updateJobEntry.feature"}]